.gitignore
.gitmodules
CMakeLists.txt
LICENSE
README.md
pyproject.toml
requirements.txt
setup.py
.github/workflows/CI.yml
.github/workflows/python-publish.yml
src/include/cell.cpp
src/include/graph.cpp
src/matenv/__init__.py
src/matenv/cell.py
src/matenv.egg-info/PKG-INFO
src/matenv.egg-info/SOURCES.txt
src/matenv.egg-info/dependency_links.txt
src/matenv.egg-info/requires.txt
src/matenv.egg-info/top_level.txt
test/__init__.py
test/test_c_cell.py
test/test_cell.py
test/test_matenv.py