Metadata-Version: 2.1
Name: matenv
Version: 0.0.1
Summary: Physical environment framework for molecules and crystals.
Home-page: https://github.com/yaozhenghangma/matenv/
Author: Yaozhenghang Ma
Author-email: Yaozhenghang.Ma@gmail.com
License: GNU GPLv3
Project-URL: Bug Tracker, https://github.com/yaozhenghangma/matenv/issues/
Project-URL: Documentation, https://matenv.readthedocs.io/
Platform: UNKNOWN
Requires-Python: >=3.8
Provides-Extra: test
License-File: LICENSE
